nonebot/adapters/discord/__init__.py
nonebot/adapters/discord/adapter.py
nonebot/adapters/discord/api/__init__.py
nonebot/adapters/discord/api/client.py
nonebot/adapters/discord/api/client.pyi
nonebot/adapters/discord/api/handle.py
nonebot/adapters/discord/api/model.py
nonebot/adapters/discord/api/request.py
nonebot/adapters/discord/api/types.py
nonebot/adapters/discord/api/utils.py
nonebot/adapters/discord/bot.py
nonebot/adapters/discord/commands/__init__.py
nonebot/adapters/discord/commands/matcher.py
nonebot/adapters/discord/commands/params.py
nonebot/adapters/discord/commands/storage.py
nonebot/adapters/discord/config.py
nonebot/adapters/discord/event.py
nonebot/adapters/discord/exception.py
nonebot/adapters/discord/message.py
nonebot/adapters/discord/payload.py
nonebot/adapters/discord/utils.py
nonebot_adapter_discord-0.1.8.dist-info/METADATA
nonebot_adapter_discord-0.1.8.dist-info/WHEEL
nonebot_adapter_discord-0.1.8.dist-info/RECORD
