Metadata-Version: 2.1
Name: nonebot-adapter-discord
Version: 0.1.8
Summary: Discord adapter for nonebot2
Home-page: https://github.com/nonebot/adapter-discord
License: MIT
Keywords: nonebot,discord,bot
Author: CMHopeSunshine
Author-email: 277073121@qq.com
Requires-Python: >=3.9,<4.0
Classifier: License :: OSI Approved :: MIT License
Classifier: Programming Language :: Python :: 3
Classifier: Programming Language :: Python :: 3.9
Classifier: Programming Language :: Python :: 3.10
Classifier: Programming Language :: Python :: 3.11
Classifier: Programming Language :: Python :: 3.12
Requires-Dist: nonebot2 (>=2.2.1,<3.0.0)
Project-URL: Documentation, https://github.com/nonebot/adapter-discord
Project-URL: Repository, https://github.com/nonebot/adapter-discord
